pulumiverse_sentry/__init__.py
pulumiverse_sentry/_inputs.py
pulumiverse_sentry/_utilities.py
pulumiverse_sentry/get_sentry_dashboard.py
pulumiverse_sentry/get_sentry_issue_alert.py
pulumiverse_sentry/get_sentry_key.py
pulumiverse_sentry/get_sentry_metric_alert.py
pulumiverse_sentry/get_sentry_organization.py
pulumiverse_sentry/get_sentry_organization_integration.py
pulumiverse_sentry/get_sentry_team.py
pulumiverse_sentry/outputs.py
pulumiverse_sentry/provider.py
pulumiverse_sentry/pulumi-plugin.json
pulumiverse_sentry/py.typed
pulumiverse_sentry/sentry_dashboard.py
pulumiverse_sentry/sentry_issue_alert.py
pulumiverse_sentry/sentry_key.py
pulumiverse_sentry/sentry_metric_alert.py
pulumiverse_sentry/sentry_organization.py
pulumiverse_sentry/sentry_organization_code_mapping.py
pulumiverse_sentry/sentry_organization_member.py
pulumiverse_sentry/sentry_organization_repository_github.py
pulumiverse_sentry/sentry_plugin.py
pulumiverse_sentry/sentry_project.py
pulumiverse_sentry/sentry_rule.py
pulumiverse_sentry/sentry_team.py
pulumiverse_sentry/config/__init__.py
pulumiverse_sentry/config/__init__.pyi
pulumiverse_sentry/config/vars.py
pulumiverse_sentry-0.0.9.dist-info/METADATA
pulumiverse_sentry-0.0.9.dist-info/WHEEL
pulumiverse_sentry-0.0.9.dist-info/top_level.txt
pulumiverse_sentry-0.0.9.dist-info/RECORD
