Metadata-Version: 2.1
Name: pulumiverse_sentry
Version: 0.0.9
Summary: A Pulumi package for creating and managing Sentry resources.
License: Apache-2.0
Project-URL: Homepage, https://github.com/pulumiverse
Project-URL: Repository, https://github.com/pulumiverse/pulumi-sentry
Keywords: pulumi,sentry,category/cloud
Requires-Python: >=3.8
Requires-Dist: parver >=0.2.1
Requires-Dist: pulumi <4.0.0,>=3.0.0
Requires-Dist: semver >=2.8.1
Requires-Dist: typing-extensions >=4.11 ; python_version < "3.11"
